cognite/model_hosting/_cognite_model_hosting_common/__init__.py
cognite/model_hosting/_cognite_model_hosting_common/utils.py
cognite/model_hosting/_cognite_model_hosting_common/version.py
cognite/model_hosting/data_fetcher/__init__.py
cognite/model_hosting/data_fetcher/_cdp_client.py
cognite/model_hosting/data_fetcher/data_fetcher.py
cognite/model_hosting/data_fetcher/exceptions.py
cognite/model_hosting/data_spec/__init__.py
cognite/model_hosting/data_spec/data_spec.py
cognite/model_hosting/data_spec/exceptions.py
cognite/model_hosting/schedules/__init__.py
cognite/model_hosting/schedules/exceptions.py
cognite/model_hosting/schedules/schedules.py
cognite_model_hosting-0.2.0.dist-info/LICENSE
cognite_model_hosting-0.2.0.dist-info/METADATA
cognite_model_hosting-0.2.0.dist-info/WHEEL
cognite_model_hosting-0.2.0.dist-info/top_level.txt
cognite_model_hosting-0.2.0.dist-info/RECORD
